undated/__init__.py
undated/_core.py
undated/_data.py
undated/_tools.py
undated/fmts.py
undated/utils.py
undated-1.0.8.dist-info/LICENSE
undated-1.0.8.dist-info/METADATA
undated-1.0.8.dist-info/WHEEL
undated-1.0.8.dist-info/top_level.txt
undated-1.0.8.dist-info/RECORD
