Metadata-Version: 2.1
Name: undated
Version: 1.0.8
Summary: For when dates aren't dates
Home-page: https://github.com/rikfair/undated
Author: rikfair
Author-email: mail4rik-pypi@yahoo.com
License: MIT
Project-URL: Bug Tracker, https://github.com/rikfair/undated/issues
Project-URL: Documentation, https://undated.readthedocs.io/
Classifier: Development Status :: 5 - Production/Stable
Classifier: Intended Audience :: Developers
Classifier: License :: OSI Approved :: MIT License
Classifier: Operating System :: OS Independent
Classifier: Programming Language :: Python :: 3
Classifier: Programming Language :: Python :: 3 :: Only
Classifier: Topic :: Database
Classifier: Topic :: Office/Business :: Financial
Classifier: Topic :: Office/Business :: Financial :: Accounting
Classifier: Topic :: Office/Business :: Financial :: Investment
Classifier: Topic :: Office/Business :: Financial :: Spreadsheet
Classifier: Topic :: Text Processing :: General
Classifier: Topic :: Utilities
Requires-Python: >=3.7
License-File: LICENSE
